{
  "packages":
  [
    {
      "name": "GridGuard_BLE",
      "maintainer": "Varda AS",
      "websiteURL": "https://gridguard.no",
      "email" : "crishan@varda.as",
      "platforms":
      [
        {
          "name": "GridGuard BLE",
          "architecture": "mbed",
          "version": "1.0.2",
          "category": "GridGuard",
          "url": "https://raw.githubusercontent.com/Gridguard/GridGuard-Arduino/main/based_on_BLE_nano_33/gridguard_ble_1.0.2.zip",
          "archiveFileName": "gridguard_ble_1.0.2.zip",
          "checksum": "SHA-256:E26B73586F61494347BC980D8B1D99D6324E6A38C39687925F903A4EB9CCA54A",
          "size": "9793102",
          
          "boards": [
            {
              "name": "gridguard_ble"
            }
          ]
        }
        
      ]
    }
  ]
}